<?xml version="1.0" encoding="UTF-8"?>
<Manifest xmlns:xsi="http://www.w3.org/2001/XMLSchema-instance" xsdVersion="0.12.0" kind="BinaryCode" efmiVersion="1.0.0" id="{50e01e19-05b9-4fe9-b7a6-135a8d37a142}" name="BCode_SPE_fba3e0dfa6c8985b41bcbe3594ee941ce98b740c_b48b2d90fa045262ae3c2a0df7ec20da237e1e13" generationDateAndTime="2026-03-04T10:50:38Z" generationTool="ESP" xsi:noNamespaceSchemaLocation="../schemas/BinaryCode/efmiBinaryCodeManifest.xsd">
    <ManifestReferences>
        <ManifestReference id="PROD_MAN_ID" manifestRefId="{bf42e704-e2ed-4098-ad9e-06330099503d}" checksum="1e640f3d35d8a44a6e03388de8bacbe7d110e2a8" origin="true"/>
    </ManifestReferences>
    <Files>
        <File id="FILE_ID_block.obj_0" name="block.obj" path="./" needsChecksum="true" checksum="1fee1d9eb9670b43dbffa1c9b1da18499adc482b" role="Code"/>
        <File id="FILE_ID_galec_stl.obj_1" name="galec_stl.obj" path="./" needsChecksum="true" checksum="0c40790065575ce5c079963a854ad11e6993ed31" role="Code"/>
        <File id="FILE_ID_sii_block_interface.obj_2" name="sii_block_interface.obj" path="./" needsChecksum="true" checksum="eff51f8c0ed25e61f8719e5345b14120d1842fcc" role="Code"/>
        <File id="FILE_ID_mei_block_interface.obj_3" name="mei_block_interface.obj" path="./" needsChecksum="true" checksum="f2167be573e536696e678975e18f520ea8fb20f2" role="Code"/>
        <File id="FILE_ID_block.lib_4" name="block.lib" path="./" needsChecksum="true" checksum="2fcf135a4ae1a60984533cf3236f43f642bbd204" role="other"/>
        <File id="FILE_ID_makefile_5" name="makefile" path="./" needsChecksum="true" checksum="a2ad0a9b031581a95f5815ae94556db4add5604e" role="other"/>
    </Files>
    <BinaryContainer>
        <BuildConfiguration>
            <Compiler id="COMPILER_ID" vendor="Microsoft" name="VS" version="Microsoft (R) C/C++ Optimizing Compiler Version 19.34.31944 for x64" executableName="cl"/>
            <Linker vendor="Microsoft" name="VS" version="Microsoft (R) C/C++ Optimizing Compiler Version 19.34.31944 for x64" executableName="lib"/>
            <CompilerOptionSets>
                <CompilerOptionSet id="CMPOPTSET_ID_default_0" compilerRefId="COMPILER_ID">
                    <CompilerOptions compileRoot="./default">
                        <CompilerSwitch index="1" id="CMPOPT_ID_0" name="nologo"/>
                        <CompilerSwitch index="2" id="CMPOPT_ID_1" name="O2"/>
                        <CompilerSwitch index="3" id="CMPOPT_ID_2" name="std" value="c17"/>
                        <CompilerSwitch index="4" id="CMPOPT_ID_3" name="W4"/>
                    </CompilerOptions>
                </CompilerOptionSet>
            </CompilerOptionSets>
            <DefaultCompilerOptions compilerOptionsRefId="CMPOPTSET_ID_default_0"/>
            <LinkerOptionSet>
                <LinkerOptions>
                    <LinkerSwitch index="1" id="LKROPT_ID_0" name="nologo"/>
                </LinkerOptions>
            </LinkerOptionSet>
            <CompileTarget vendor="" targetName="Win64" chipVersion="" instructionSetArchitecture="x86-64" endianess="little" registerWidth="64" addressWidth="64"/>
        </BuildConfiguration>
        <Modules>
            <BinaryModule id="BINMOD_ID_0" generationTool="ESP" generationDateAndTime="2026-03-04T10:50:38Z" compilerOptionSetRefId="default">
                <ObjectFile id="OBJFILE_ID_0">
                    <FileReference fileRefId="FILE_ID_block.obj_0"/>
                    <ForeignSourceFileReference manifestReferenceRefId="PROD_MAN_ID" foreignRefId="FILE_ID_block.c_0"/>
                </ObjectFile>
            </BinaryModule>
            <BinaryModule id="BINMOD_ID_1" generationTool="ESP" generationDateAndTime="2026-03-04T10:50:38Z" compilerOptionSetRefId="default">
                <ObjectFile id="OBJFILE_ID_1">
                    <FileReference fileRefId="FILE_ID_galec_stl.obj_1"/>
                    <ForeignSourceFileReference manifestReferenceRefId="PROD_MAN_ID" foreignRefId="FILE_ID_galec_stl.c_1"/>
                </ObjectFile>
            </BinaryModule>
            <BinaryModule id="BINMOD_ID_2" generationTool="ESP" generationDateAndTime="2026-03-04T10:50:38Z" compilerOptionSetRefId="default">
                <ObjectFile id="OBJFILE_ID_2">
                    <FileReference fileRefId="FILE_ID_sii_block_interface.obj_2"/>
                    <ForeignSourceFileReference manifestReferenceRefId="PROD_MAN_ID" foreignRefId="FILE_ID_sii_block_interface.c_3"/>
                </ObjectFile>
            </BinaryModule>
            <BinaryModule id="BINMOD_ID_3" generationTool="ESP" generationDateAndTime="2026-03-04T10:50:38Z" compilerOptionSetRefId="default">
                <ObjectFile id="OBJFILE_ID_3">
                    <FileReference fileRefId="FILE_ID_mei_block_interface.obj_3"/>
                    <ForeignSourceFileReference manifestReferenceRefId="PROD_MAN_ID" foreignRefId="FILE_ID_mei_block_interface.c_4"/>
                </ObjectFile>
            </BinaryModule>
        </Modules>
        <BinaryContainerInfo/>
    </BinaryContainer>
</Manifest>
