<?xml version="1.0" encoding="UTF-8"?>
<Manifest xmlns:xsi="http://www.w3.org/2001/XMLSchema-instance" xsdVersion="0.12.0" kind="BinaryCode" efmiVersion="1.0.0" id="{4a4d85e1-d5da-4940-9839-f6c93e9abc26}" name="BCode_SPE_cb4a8a449b4ada864625ee5a4355578a3aaf08ed_b48b2d90fa045262ae3c2a0df7ec20da237e1e13" generationDateAndTime="2026-03-12T02:57:17Z" generationTool="ESP" xsi:noNamespaceSchemaLocation="../schemas/BinaryCode/efmiBinaryCodeManifest.xsd">
    <ManifestReferences>
        <ManifestReference id="PROD_MAN_ID" manifestRefId="{2e0d5f32-02de-481c-9440-67f86a27bda8}" checksum="fde5f8d63bfbac5c59a3e3c4760f7a270285c94e" origin="true"/>
    </ManifestReferences>
    <Files>
        <File id="FILE_ID_galec_stl.obj_0" name="galec_stl.obj" path="./" needsChecksum="true" checksum="8827c58f33d422f632269308d6f89813267a6e74" role="Code"/>
        <File id="FILE_ID_block.obj_1" name="block.obj" path="./" needsChecksum="true" checksum="14dac3771620e39b2e9185f16ecc0379585d3de6" role="Code"/>
        <File id="FILE_ID_sii_block_interface.obj_2" name="sii_block_interface.obj" path="./" needsChecksum="true" checksum="939b39e38ac828e18cf4315ad8592d1da4ed766c" role="Code"/>
        <File id="FILE_ID_mei_block_interface.obj_3" name="mei_block_interface.obj" path="./" needsChecksum="true" checksum="1c95eb23a6f13aeb484e6bd931881280c7f23874" role="Code"/>
        <File id="FILE_ID_block.lib_4" name="block.lib" path="./" needsChecksum="true" checksum="181b3813b002f5b487ab17f47b66b41cea4d5b86" role="other"/>
        <File id="FILE_ID_makefile_5" name="makefile" path="./" needsChecksum="true" checksum="1e5d97c3fa77d5415483cf78c7462d1d247244f4" role="other"/>
    </Files>
    <BinaryContainer>
        <BuildConfiguration>
            <Compiler id="COMPILER_ID" vendor="Microsoft" name="VS" version="Microsoft (R) C/C++ Optimizing Compiler Version 19.44.35224 for x64" executableName="cl"/>
            <Linker vendor="Microsoft" name="VS" version="Microsoft (R) C/C++ Optimizing Compiler Version 19.44.35224 for x64" executableName="lib"/>
            <CompilerOptionSets>
                <CompilerOptionSet id="CMPOPTSET_ID_default_0" compilerRefId="COMPILER_ID">
                    <CompilerOptions compileRoot="./default">
                        <CompilerSwitch index="1" id="CMPOPT_ID_0" name="nologo"/>
                        <CompilerSwitch index="2" id="CMPOPT_ID_1" name="O2"/>
                        <CompilerSwitch index="3" id="CMPOPT_ID_2" name="std" value="c17"/>
                        <CompilerSwitch index="4" id="CMPOPT_ID_3" name="W4"/>
                    </CompilerOptions>
                </CompilerOptionSet>
            </CompilerOptionSets>
            <DefaultCompilerOptions compilerOptionsRefId="CMPOPTSET_ID_default_0"/>
            <LinkerOptionSet>
                <LinkerOptions>
                    <LinkerSwitch index="1" id="LKROPT_ID_0" name="nologo"/>
                </LinkerOptions>
            </LinkerOptionSet>
            <CompileTarget vendor="" targetName="Win64" chipVersion="" instructionSetArchitecture="x86-64" endianess="little" registerWidth="64" addressWidth="64"/>
        </BuildConfiguration>
        <Modules>
            <BinaryModule id="BINMOD_ID_0" generationTool="ESP" generationDateAndTime="2026-03-12T02:57:17Z" compilerOptionSetRefId="default">
                <ObjectFile id="OBJFILE_ID_0">
                    <FileReference fileRefId="FILE_ID_galec_stl.obj_0"/>
                    <ForeignSourceFileReference manifestReferenceRefId="PROD_MAN_ID" foreignRefId="FILE_ID_galec_stl.c_0"/>
                </ObjectFile>
            </BinaryModule>
            <BinaryModule id="BINMOD_ID_1" generationTool="ESP" generationDateAndTime="2026-03-12T02:57:17Z" compilerOptionSetRefId="default">
                <ObjectFile id="OBJFILE_ID_1">
                    <FileReference fileRefId="FILE_ID_block.obj_1"/>
                    <ForeignSourceFileReference manifestReferenceRefId="PROD_MAN_ID" foreignRefId="FILE_ID_block.c_3"/>
                </ObjectFile>
            </BinaryModule>
            <BinaryModule id="BINMOD_ID_2" generationTool="ESP" generationDateAndTime="2026-03-12T02:57:17Z" compilerOptionSetRefId="default">
                <ObjectFile id="OBJFILE_ID_2">
                    <FileReference fileRefId="FILE_ID_sii_block_interface.obj_2"/>
                    <ForeignSourceFileReference manifestReferenceRefId="PROD_MAN_ID" foreignRefId="FILE_ID_sii_block_interface.c_7"/>
                </ObjectFile>
            </BinaryModule>
            <BinaryModule id="BINMOD_ID_3" generationTool="ESP" generationDateAndTime="2026-03-12T02:57:17Z" compilerOptionSetRefId="default">
                <ObjectFile id="OBJFILE_ID_3">
                    <FileReference fileRefId="FILE_ID_mei_block_interface.obj_3"/>
                    <ForeignSourceFileReference manifestReferenceRefId="PROD_MAN_ID" foreignRefId="FILE_ID_mei_block_interface.c_8"/>
                </ObjectFile>
            </BinaryModule>
        </Modules>
        <BinaryContainerInfo/>
    </BinaryContainer>
</Manifest>
